ansible/__init__.py
ansible/ec2.py
ansible/iam.py
ansible/key_pair.py
docker/__init__.py
docker/ec2.py
docker/iam.py
docker/key_pair.py
jenkins/__init__.py
jenkins/ec2.py
jenkins/iam.py
jenkins/key_pair.py
kubernetes/__init__.py
kubernetes/ec2.py
kubernetes/iam.py
kubernetes/key_pair.py
linux/__init__.py
linux/ticket1.py
linux/ticket2.py
linux/ticket3.py
terraforms/__init__.py
terraforms/ec2.py
terraforms/iam.py
terraforms/key_pair.py
terraforms_farrukh90-0.0.14.dist-info/LICENSE
terraforms_farrukh90-0.0.14.dist-info/METADATA
terraforms_farrukh90-0.0.14.dist-info/WHEEL
terraforms_farrukh90-0.0.14.dist-info/top_level.txt
terraforms_farrukh90-0.0.14.dist-info/RECORD
